taskiq_cancellation/__about__.py
taskiq_cancellation/__init__.py
taskiq_cancellation/exceptions.py
taskiq_cancellation/message.py
taskiq_cancellation/py.typed
taskiq_cancellation/utils.py
taskiq_cancellation/abc/__init__.py
taskiq_cancellation/abc/backend.py
taskiq_cancellation/abc/notifier.py
taskiq_cancellation/abc/started_listening_event.py
taskiq_cancellation/abc/state_holder.py
taskiq_cancellation/backends/__init__.py
taskiq_cancellation/backends/in_memory.py
taskiq_cancellation/backends/modular.py
taskiq_cancellation/backends/redis.py
taskiq_cancellation/cancellation_handlers/__init__.py
taskiq_cancellation/cancellation_handlers/cancellation_type.py
taskiq_cancellation/cancellation_handlers/edge_3_11.py
taskiq_cancellation/cancellation_handlers/edge_non_supported.py
taskiq_cancellation/cancellation_handlers/level.py
taskiq_cancellation/notifiers/__init__.py
taskiq_cancellation/notifiers/aiopika.py
taskiq_cancellation/notifiers/in_memory.py
taskiq_cancellation/notifiers/null.py
taskiq_cancellation/notifiers/queue.py
taskiq_cancellation/notifiers/redis.py
taskiq_cancellation/state_holders/__init__.py
taskiq_cancellation/state_holders/in_memory.py
taskiq_cancellation/state_holders/null.py
taskiq_cancellation/state_holders/redis.py
taskiq_cancellation-0.0.1.dist-info/METADATA
taskiq_cancellation-0.0.1.dist-info/WHEEL
taskiq_cancellation-0.0.1.dist-info/licenses/LICENSE.txt
taskiq_cancellation-0.0.1.dist-info/RECORD
