Metadata-Version: 2.4
Name: taskiq-cancellation
Version: 0.0.1
Summary: Task cancellation for taskiq
Project-URL: Documentation, https://github.com/ACherryJam/taskiq-cancellation#readme
Project-URL: Issues, https://github.com/ACherryJam/taskiq-cancellation/issues
Project-URL: Source, https://github.com/ACherryJam/taskiq-cancellation
Author-email: Alexander Starikov <acherryjam@gmail.com>
License-Expression: MIT
License-File: LICENSE.txt
Keywords: cancellation,taskiq
Classifier: Development Status :: 4 - Beta
Classifier: Programming Language :: Python
Classifier: Programming Language :: Python :: 3.9
Classifier: Programming Language :: Python :: 3.10
Classifier: Programming Language :: Python :: 3.11
Classifier: Programming Language :: Python :: 3.12
Classifier: Programming Language :: Python :: 3.13
Classifier: Programming Language :: Python :: 3.14
Classifier: Programming Language :: Python :: Implementation :: CPython
Classifier: Programming Language :: Python :: Implementation :: PyPy
Requires-Python: >=3.9
Requires-Dist: async-timeout>=5.0.1; python_full_version < '3.11'
Requires-Dist: taskiq
Requires-Dist: typing-extensions>=4.15.0; python_full_version < '3.11'
Provides-Extra: aiopika
Requires-Dist: aio-pika; extra == 'aiopika'
Provides-Extra: redis
Requires-Dist: redis~=6.0; extra == 'redis'
